wp_dt/__init__.py
wp_dt/project.py
wp_dt/wp.py
wp_dt-0.0.6.dist-info/LICENSE
wp_dt-0.0.6.dist-info/WHEEL
wp_dt-0.0.6.dist-info/METADATA
wp_dt-0.0.6.dist-info/RECORD
